{
    "LoMolLeOcc": {
        "centers": [
            [
                180,
                -5
            ]
        ],
        "gains": [
            [
                13,
                40
            ]
        ]
    },
    "LoMolLeExt": {
        "centers": [
            [
                -115,
                -7
            ]
        ],
        "gains": [
            [
                23,
                40
            ]
        ]
    },
    "LoMolLeInt": {
        "centers": [
            [
                125,
                -7
            ]
        ],
        "gains": [
            [
                18,
                40
            ]
        ]
    },
    "LoMolRiOcc": {
        "centers": [
            [
                180,
                -7
            ]
        ],
        "gains": [
            [
                13,
                40
            ]
        ]
    },
    "LoMolRiExt": {
        "centers": [
            [
                115,
                -7
            ]
        ],
        "gains": [
            [
                23,
                40
            ]
        ]
    },
    "LoMolRiInt": {
        "centers": [
            [
                -125,
                -7
            ]
        ],
        "gains": [
            [
                18,
                40
            ]
        ]
    },
    "LoIncExt": {
        "centers": [
            [
                110,
                -1
            ],
            [
                -110,
                -1
            ]
        ],
        "gains": [
            [
                30,
                40
            ],
            [
                30,
                40
            ]
        ]
    },
    "LoIncInt": {
        "centers": [
            [
                180,
                -7
            ],
            [
                -115,
                0
            ],
            [
                115,
                0
            ]
        ],
        "gains": [
            [
                20,
                40
            ],
            [
                20,
                40
            ],
            [
                20,
                40
            ]
        ]
    },
    "UpMolLeOcc": {
        "centers": [
            [
                0,
                -1
            ],
            [
                0,
                -7
            ]
        ],
        "gains": [
            [
                13,
                40
            ],
            [
                13,
                40
            ]
        ]
    },
    "UpMolLeExt": {
        "centers": [
            [
                -65,
                -7
            ]
        ],
        "gains": [
            [
                23,
                40
            ]
        ]
    },
    "UpMolLeInt": {
        "centers": [
            [
                55,
                -5
            ]
        ],
        "gains": [
            [
                18,
                40
            ]
        ]
    },
    "UpMolRiOcc": {
        "centers": [
            [
                0,
                -5
            ]
        ],
        "gains": [
            [
                13,
                40
            ]
        ]
    },
    "UpMolRiExt": {
        "centers": [
            [
                65,
                -3
            ]
        ],
        "gains": [
            [
                23,
                40
            ]
        ]
    },
    "UpMolRiInt": {
        "centers": [
            [
                -55,
                -5
            ]
        ],
        "gains": [
            [
                18,
                40
            ]
        ]
    },
    "UpIncExt": {
        "centers": [
            [
                65,
                -1
            ],
            [
                -65,
                -1
            ]
        ],
        "gains": [
            [
                25,
                40
            ],
            [
                25,
                40
            ]
        ]
    },
    "UpIncInt": {
        "centers": [
            [
                0,
                -7
            ],
            [
                45,
                0
            ],
            [
                -45,
                0
            ]
        ],
        "gains": [
            [
                20,
                40
            ],
            [
                20,
                40
            ],
            [
                20,
                40
            ]
        ]
    },
    "version": 1,
    "revision": 3,
    "threshold": 2
}
